schedulify/.dockerignore
schedulify/Dockerfile
schedulify/__init__.py
schedulify-0.0.3.dist-info/LICENSE.txt
schedulify-0.0.3.dist-info/METADATA
schedulify-0.0.3.dist-info/WHEEL
schedulify-0.0.3.dist-info/entry_points.txt
schedulify-0.0.3.dist-info/top_level.txt
schedulify-0.0.3.dist-info/RECORD
