Metadata-Version: 2.1
Name: schedulify
Version: 0.0.3
Summary: Schedule Python functions on Google Cloud Platform with minimal boilerplate
Home-page: https://github.com/aryann/schedulify
Author: Aryan Naraghi
Author-email: aryan.naraghi@gmail.com
License: UNKNOWN
Project-URL: Source Code, https://github.com/aryann/schedulify
Project-URL: Author's Website, https://aryan.app
Platform: UNKNOWN
Classifier: Development Status :: 2 - Pre-Alpha
Classifier: Environment :: Console
Classifier: Intended Audience :: Developers
Classifier: License :: OSI Approved :: Apache Software License
Classifier: Programming Language :: Python :: 3.6
Classifier: Programming Language :: Python :: 3.7
Classifier: Topic :: Utilities
Requires-Python: >=3.6
